{
  "meta": {
    "stableOrder": true
  },
  "lockfileVersion": 3,
  "ATTENTION": "THIS IS AN AUTOGENERATED FILE. DO NOT EDIT THIS FILE DIRECTLY.",
  "specifiers": {
    "common@../common": "common@../common",
    "imagegeneration@../feature/imageGeneration": "imagegeneration@../feature/imageGeneration",
    "main@../feature/main": "main@../feature/main",
    "model@../feature/model": "model@../feature/model",
    "setting@../feature/setting": "setting@../feature/setting"
  },
  "packages": {
    "common@../common": {
      "name": "common",
      "version": "1.0.0",
      "resolved": "../common",
      "registryType": "local",
      "packageType": "InterfaceHar"
    },
    "imagegeneration@../feature/imageGeneration": {
      "name": "imagegeneration",
      "version": "1.0.0",
      "resolved": "../feature/imageGeneration",
      "registryType": "local",
      "dependencies": {
        "common": "file:../../common"
      },
      "packageType": "InterfaceHar"
    },
    "main@../feature/main": {
      "name": "main",
      "version": "1.0.0",
      "resolved": "../feature/main",
      "registryType": "local",
      "dependencies": {
        "common": "file:../../common"
      },
      "packageType": "InterfaceHar"
    },
    "model@../feature/model": {
      "name": "model",
      "version": "1.0.0",
      "resolved": "../feature/model",
      "registryType": "local",
      "dependencies": {
        "common": "file:../../common"
      },
      "packageType": "InterfaceHar"
    },
    "setting@../feature/setting": {
      "name": "setting",
      "version": "1.0.0",
      "resolved": "../feature/setting",
      "registryType": "local",
      "dependencies": {
        "common": "file:../../common"
      },
      "packageType": "InterfaceHar"
    }
  }
}